skcan_compare/__init__.py
skcan_compare/globals.py
skcan_compare/query.py
skcan_compare/visualize.py
skcan_compare/data/coords_human.json
skcan_compare-0.0.3.dist-info/LICENSE
skcan_compare-0.0.3.dist-info/METADATA
skcan_compare-0.0.3.dist-info/WHEEL
skcan_compare-0.0.3.dist-info/top_level.txt
skcan_compare-0.0.3.dist-info/RECORD
