Metadata-Version: 2.1
Name: skcan-compare
Version: 0.0.3
Summary: A package for retrieving and visualizing data contained in     SCKAN (e.g., across species, relationship to spinal segments) to highlight similarities and differences in neuronal pathways
Author: Shailesh Appukuttan, Hiba Ben Aribi, Pranjal Garg, Gautam Kumar
Author-email: appukuttan.shailesh@gmail.com
License: Apache-2.0
License-File: LICENSE
